[
    {
        "id": "Battleborn",
        "title": "Battleborn",
        "description": "Card 1",
        "url": "Imagens%20Jogos/Nintendo/2KDrive"

    },

    {
        "id": "Ben10",
        "title": "Bem 10: Uma super viagem",
        "description": "Card 2",
        "url": "Imagens%20Jogos/PS3/CrashBandicootTrilogia"

    },

    {
        "id": "LegoMovie2",
        "title": "Lego Movie 2",
        "description": "Card 3",
        "url": "Imagens%20Jogos/PS4/BloodBowl"

    },
   
    
    {
        "id": "RUGBY15",
        "title": "Bem 10: Uma super viagem",
        "description": "Card 4",
        "url": "Imagens%20Jogos/PS5/GoodOfWarRagnarok"

    },

    {
        "id": "Battleborn1",
        "title": "Battleborn",
        "description": "Card 5",
        "url": "Imagens%20Jogos/Xbox360/Destiny"

    },

    {
        "id": "Ben11",
        "title": "Bem 10: Uma super viagem",
        "description": "Card 6",
        "url": "Imagens%20Jogos/XboxOne/LegoMovie2"

    },
    {
        "id": "OsIncriveis",
        "title": "Bem 10: Uma super viagem",
        "description": "Card 7",
        "url": "Imagens%20Jogos/XboxOne/OsIncriveis"

    }
]
